tensorage/__init__.py
tensorage/__version__.py
tensorage/auth.py
tensorage/session.py
tensorage/store.py
tensorage/types.py
tensorage/backend/__init__.py
tensorage/backend/base.py
tensorage/backend/database.py
tensorage/backend/storage.py
tensorage/sql/__init__.py
tensorage/sql/sql.py
tests/__init__.py
tests/test_auth.py
tests/test_database.py
tests/test_store.py
tensorage-0.1.7.dist-info/LICENSE
tensorage-0.1.7.dist-info/METADATA
tensorage-0.1.7.dist-info/WHEEL
tensorage-0.1.7.dist-info/top_level.txt
tensorage-0.1.7.dist-info/RECORD
