Metadata-Version: 2.1
Name: tensorage
Version: 0.1.7
Summary: Storing tensors in a supabase backend
Author: Mirko Mälicke
Author-email: mirko@hydrocode.de
License-File: LICENSE
Requires-Dist: typing-extensions
Requires-Dist: supabase
Requires-Dist: python-dotenv
Requires-Dist: numpy
Requires-Dist: xarray
Requires-Dist: tqdm
